more_peekable/__init__.py
more_peekable/py.typed
tests/__init__.py
more_peekable-0.1.0.dist-info/LICENSE
more_peekable-0.1.0.dist-info/METADATA
more_peekable-0.1.0.dist-info/WHEEL
more_peekable-0.1.0.dist-info/top_level.txt
more_peekable-0.1.0.dist-info/RECORD
