Metadata-Version: 2.1
Name: more_peekable
Version: 0.1.0
Summary: Extends the peekable class from more-itertools
Home-page: https://github.com/ernieIzde8ski/more-itertools
Author: Ernie Izdebski
License: MIT
Classifier: Programming Language :: Python :: 3
Classifier: License :: OSI Approved :: MIT License
Classifier: Operating System :: OS Independent
License-File: LICENSE
